slack_timezoner/__init__.py
slack_timezoner/group_by_timezones.py
slack_timezoner-0.1.3.dist-info/entry_points.txt
slack_timezoner-0.1.3.dist-info/WHEEL
slack_timezoner-0.1.3.dist-info/METADATA
slack_timezoner-0.1.3.dist-info/RECORD
