Metadata-Version: 2.1
Name: slack-timezoner
Version: 0.1.3
Summary: A toy app to give a breakdown of timezone distribution in a slack workgroup
Home-page: https://github.com/mrchrisadams/slack-timezoner
License: Apache-2.0
Author: Chris Adams
Author-email: chris@productscience.co.uk
Requires-Python: >=3.6
Classifier: License :: OSI Approved :: Apache Software License
Classifier: Programming Language :: Python :: 3
Classifier: Programming Language :: Python :: 3.6
Classifier: Programming Language :: Python :: 3.7
Classifier: Programming Language :: Python :: 3.8
Requires-Dist: django (>=3.0.8,<4.0.0)
Requires-Dist: python-dotenv[cli] (>=0.14.0,<0.15.0)
Requires-Dist: slackclient (>=2.7.2,<3.0.0)
Project-URL: Repository, https://github.com/mrchrisadams/slack-timezoner
